<?xml version="1.0" encoding="UTF-8"?>
<!--
  ****************************************************************
ERmodel_v1.2/instances/catalogue/src/conceptualModels/2RegularHypergraph.xml 
****************************************************************

Copyright 2016, 2107 Cyprotex Discovery Ltd.

This file is part of the the ERmodel suite of models and transforms.

The ERmodel suite is free software: you can redistribute it and/or modify
it under the terms of the GNU General Public License as published by
the Free Software Foundation, either version 3 of the License, or
(at your option) any later version.

ERmodel suite is distributed in the hope that it will be useful,
but WITHOUT ANY WARRANTY; without even the implied warranty of
MERCHANTABILITY or FITNESS FOR A PARTICULAR PURPOSE.  See the
GNU General Public License for more details.

You should have received a copy of the GNU General Public License
along with this program.  If not, see <http://www.gnu.org/licenses/>.
****************************************************************
-->
<entity_model xmlns="http://www.entitymodelling.org/ERmodel">
   <entity_type>
      <name>person</name>
      <presentation>
         <x>0.2</x>
         <y>0.2</y>
         <w>2.0</w>
      </presentation>
      <attribute xmlns:era="http://www.entitymodelling.org/ERmodel">
         <name>name</name>
         <type>
            <string/>
         </type>
         <optional/>
      </attribute>
      <attribute xmlns:era="http://www.entitymodelling.org/ERmodel">
         <name>date of birth</name>
         <type>
            <string/>
         </type>
         <optional/>
      </attribute>
   </entity_type>
</entity_model>
