<!-- 
****************************************************************
ERmodel_v1.2/instances/catalogue/src/conceptualModels/relationalMetaModel4.xml 
****************************************************************

Copyright 2016, 2107 Cyprotex Discovery Ltd.

This file is part of the the ERmodel suite of models and transforms.

The ERmodel suite is free software: you can redistribute it and/or modify
it under the terms of the GNU General Public License as published by
the Free Software Foundation, either version 3 of the License, or
(at your option) any later version.

ERmodel suite is distributed in the hope that it will be useful,
but WITHOUT ANY WARRANTY; without even the implied warranty of
MERCHANTABILITY or FITNESS FOR A PARTICULAR PURPOSE.  See the
GNU General Public License for more details.

You should have received a copy of the GNU General Public License
along with this program.  If not, see <http://www.gnu.org/licenses/>.
****************************************************************
-->

<?xml version="1.0" encoding="UTF-8"?><entity_model xmlns="http://www.entitymodelling.org/ERmodel">
<defaults><et_width>1.8</et_width><et_height>3.2</et_height></defaults>
<presentation><diagram><deltaw>1.1</deltaw><deltah>2.0</deltah></diagram></presentation>
<absolute>
   <name>relationalMetaModel</name>
   <composition>
      <name>all tables</name>
      <type>table</type>
      <cardinality>OneOrMore</cardinality>
   </composition>
</absolute>
<entity_type>
   <name>table</name>
   <presentation>
        <x>5.1</x><y>1.25</y><w>5.5</w>
   </presentation>
   <value>
      <name>name</name>
      <type>string</type>
      <identifying/>
   </value>
   <composition>
      <type>primary key column</type>
      <cardinality>OneOrMore</cardinality>
      <inverse>of</inverse>
      <id>R1</id>
      <diagram>
         <path>
             <srcattach>0.2</srcattach>
         </path>
      </diagram>
   </composition>
   <composition>
      <type>column</type>
      <cardinality>OneOrMore</cardinality>
      <inverse>of</inverse>
      <id>of</id>
      <diagram>
         <path>
           <align>ToDest</align>
         </path>
      </diagram>
   </composition>
   <composition>
      <type>foreign key</type>
      <cardinality>OneOrMore</cardinality>
      <inverse>of</inverse>
      <id>R3</id>
      <diagram>
         <path>
             <srcattach>0.8</srcattach>
         </path>
      </diagram>
   </composition>
</entity_type>
<group>
   <name>table_children</name>
    <presentation><below>table</below><x>-0.2</x><y>1.0</y></presentation>
   <entity_type>
      <name>primary key column</name>
      <!--<presentation><deltaw>0.1</deltaw></presentation>-->
      <value>
         <name>table name</name>
         <type>string</type>
         <identifying/>
         <implementationOf><rel>of</rel></implementationOf>
<!--         <implementationOf><rel>R1</rel></implementationOf> -->
      </value>  
      <value>
         <name>is column name</name>
         <type>string</type>
         <identifying/>
         <implementationOf><rel>is</rel></implementationOf>
      </value>
      <value>
         <name>seq no</name>
         <type>integer</type>
      </value>
      <dependency>
         <name>of</name>
      </dependency>
      <reference>
         <name>is</name>
         <id>R5</id>
         <cardinality>ExactlyOne</cardinality>
         <type>column</type>
         <inverse>in_primary_key</inverse>
         <diagram>
             <path>
                <align>ToSrc</align>
                <label>
                   <position>Upside</position>
                </label>
                <inverse><label><name>None</name></label></inverse>
             </path>
         </diagram>
      </reference>
   </entity_type>
   <entity_type>
       <name>column</name>
       <presentation>
            <rightOf>primary key column</rightOf>
            <x>2.75</x>
       </presentation>
       <dependency>
          <name>of</name>
       </dependency>
       <reference>
           <name>in_primary_key</name>
           <cardinality>ZeroOrOne</cardinality>
           <type>primary key column</type>
           <inverse>is</inverse>
       </reference>
      <value>
         <name>table name</name>
         <type>string</type>
         <identifying/>
         <implementationOf><rel>of</rel></implementationOf>
      </value>
       <value>
         <name>name</name>
         <type>string</type>
         <identifying/>
       </value>
   </entity_type>
   <entity_type>
       <name>foreign key</name>
       <presentation>
            <rightOf>column</rightOf>
            <x>3.0</x>
       </presentation>
       <dependency>
          <name>of</name>
       </dependency>
      <value>
         <name>table name</name>
         <type>string</type>
         <identifying/>
         <implementationOf><rel>of</rel></implementationOf>
      </value>
       <value>
          <name>name</name>
          <type>string</type>
          <identifying/>
       </value>
      <value>
         <name>to table name</name>
         <type>string</type>
         <implementationOf><rel>to</rel></implementationOf>
      </value>
       <composition>
          <type>foreign key column</type>
          <cardinality>OneOrMore</cardinality>
          <inverse>part_of</inverse>
          <id>R4</id>
          <diagram>
             <path>
                <id>
                  <label>
                     <position>Left</position>
                  </label>
                </id>
             </path>
          </diagram>
       </composition>
       <reference>
          <name>to</name>
          <id>R7</id>
          <type>table</type>
          <cardinality>ExactlyOne</cardinality>
          <diagram>
             <path>
                <srcsign>1</srcsign>
                <srcarmlen>1.2</srcarmlen>
                <destsign>-1</destsign>
                <destattach>0.666</destattach>
                <destarmlen>5.0</destarmlen>
                <vstep><absdim><src>5.5</src></absdim></vstep>
                <label>
                   <position>Upside</position>
                </label>
             </path>
          </diagram>
       </reference>
   </entity_type>
</group>
<entity_type>
    <name>foreign key column</name>
    <presentation>
         <below>foreign key</below>
         <y>0.75 </y>
         <!--<deltaw>0.1</deltaw>-->
         <name>Split</name>
    </presentation>
    <dependency>
       <name>part_of</name>
    </dependency>
      <value>
         <name>table name</name>
         <type>string</type>
         <identifying/>
         <implementationOf><rel>part_of</rel></implementationOf>
<!--
         <implementationOf><rel>R6</rel></implementationOf>
         <implementationOf><rel>R8</rel></implementationOf>
-->
      </value>
      <value>
         <name>foreign key name</name>
         <type>string</type>
         <identifying/>
         <implementationOf><rel>part_of</rel></implementationOf>
      </value>
      <value>
         <name>to column name</name>
         <type>string</type>
         <identifying/>
         <implementationOf><rel>to</rel></implementationOf>
      </value>
      <value>
         <name>column name</name>
         <type>string</type>
         <implementationOf><rel>is</rel></implementationOf>
      </value>
    <reference>
       <name>is</name>
       <id>R6</id>
       <type>column</type>
       <cardinality>ExactlyOne</cardinality>
       <diagram>
           <path>
              <srcarmlen>0.3</srcarmlen>
              <destattach>0.666</destattach>
              <destarmlen>0.3</destarmlen>
           </path>
       </diagram>
    </reference>
    <reference>
       <name>to</name>
       <id>R8</id>
       <type>primary key column</type>
       <cardinality>ExactlyOne</cardinality>
       <diagram>
          <path>
             <srcsign>1</srcsign>
             <srcarmlen>0.5</srcarmlen>
             <destsign>-1</destsign>
             <destattach>0.666</destattach>
             <destarmlen>0.5</destarmlen>
             <vstep><absdim><src>1.0</src></absdim></vstep>
             <label>
                <position>Upside</position>
             </label>
          </path>
       </diagram>
    </reference>
</entity_type>
</entity_model>
<!-- end of file: ERmodel_v1.2/instances/catalogue/src/conceptualModels/relationalMetaModel4.xml--> 

